statsbot/__init__.py
statsbot/bot.py
statsbot/cli.py
statsbot/const.py
statsbot/util.py
statsbot-0.3.1.dist-info/DESCRIPTION.rst
statsbot-0.3.1.dist-info/METADATA
statsbot-0.3.1.dist-info/RECORD
statsbot-0.3.1.dist-info/WHEEL
statsbot-0.3.1.dist-info/entry_points.txt
statsbot-0.3.1.dist-info/metadata.json
statsbot-0.3.1.dist-info/top_level.txt
