Metadata-Version: 2.0
Name: statsbot
Version: 0.3.1
Summary: Monitors and satisfies requests for subreddit_stats.
Home-page: https://github.com/bboe/statsbot
Author: Bryce Boe
Author-email: bbzbryce@gmail.com
License: Simplified BSD License
Keywords: reddit subreddit stats
Platform: UNKNOWN
Classifier: Development Status :: 4 - Beta
Classifier: Intended Audience :: Developers
Classifier: License :: OSI Approved :: BSD License
Classifier: Natural Language :: English
Classifier: Programming Language :: Python
Classifier: Programming Language :: Python :: 2.7
Classifier: Programming Language :: Python :: 3
Classifier: Programming Language :: Python :: 3.3
Classifier: Programming Language :: Python :: 3.4
Classifier: Programming Language :: Python :: 3.5
Classifier: Programming Language :: Python :: Implementation :: CPython
Requires-Dist: docopt (<1,>=0.6.2)
Requires-Dist: prawtools (>=0.23.0)
